rbs_tui_dom/__init__.py
rbs_tui_dom/entity.py
rbs_tui_dom/error.py
rbs_tui_dom/event_emitter.py
rbs_tui_dom/dom/__init__.py
rbs_tui_dom/dom/event.py
rbs_tui_dom/dom/layout.py
rbs_tui_dom/dom/style.py
rbs_tui_dom/dom/text.py
rbs_tui_dom/dom/types.py
rbs_tui_dom/extra/__init__.py
rbs_tui_dom/extra/terminal.py
rbs_tui_dom/extra/tree.py
rbs_tui_dom-1.0.2.dist-info/METADATA
rbs_tui_dom-1.0.2.dist-info/WHEEL
rbs_tui_dom-1.0.2.dist-info/top_level.txt
rbs_tui_dom-1.0.2.dist-info/RECORD
