Metadata-Version: 2.1
Name: rbs-tui-dom
Version: 1.0.2
Summary: The RBS Terminal User Interface(TUI) framework
Home-page: UNKNOWN
License: UNKNOWN
Platform: UNKNOWN
Requires-Dist: colorama
Requires-Dist: asciimatics
